dasktyping/__init__.py
dasktyping/py.typed
dasktyping/stubs/__init__.py
dasktyping/stubs/dask/__init__.pyi
dasktyping/stubs/dask/array/__init__.pyi
dasktyping/stubs/dask/bag/__init__.pyi
dasktyping/stubs/dask/dataframe/__init__.pyi
dasktyping/stubs/dask/delayed.pyi
dasktyping/stubs/dask/distributed/__init__.pyi
dasktyping/stubs/distributed/__init__.pyi
dasktyping-0.1.1.dist-info/WHEEL
dasktyping-0.1.1.dist-info/METADATA
dasktyping-0.1.1.dist-info/RECORD
